LinkList8/__init__.py
LinkList8-0.0.1.dist-info/LICENSE.txt
LinkList8-0.0.1.dist-info/METADATA
LinkList8-0.0.1.dist-info/WHEEL
LinkList8-0.0.1.dist-info/top_level.txt
LinkList8-0.0.1.dist-info/RECORD
