Metadata-Version: 2.1
Name: LinkList8
Version: 0.0.1
Summary: LinkedList operations
Home-page: 
Author: Akhil Vaitla Janardhan
Author-email: akhilvai@buffalo.edu
License: MIT
Keywords: LinkList
Platform: UNKNOWN
Classifier: Development Status :: 5 - Production/Stable
Classifier: Intended Audience :: Education
Classifier: Operating System :: Microsoft :: Windows :: Windows 10
Classifier: License :: OSI Approved :: MIT License
Classifier: Programming Language :: Python :: 3
License-File: LICENSE.txt
